{
    "name": "Cryptic crossword No 22,298", 
    "creator": {
        "webUrl": "http://www.theguardian.com/profile/rufus", 
        "name": "Rufus"
    }, 
    "dateSolutionAvailable": 998866800000, 
    "number": 22298, 
    "crosswordType": "cryptic", 
    "entries": [
        {
            "direction": "across", 
            "group": [
                "1-across"
            ], 
            "number": 1, 
            "clue": "Optical shutter (6)", 
            "separatorLocations": {}, 
            "length": 6, 
            "humanNumber": "1", 
            "position": {
                "y": 0, 
                "x": 1
            }, 
            "solution": "EYELID", 
            "id": "1-across"
        }, 
        {
            "direction": "across", 
            "group": [
                "4-across"
            ], 
            "number": 4, 
            "clue": "Bail is arranged for those with proofs of innocence (6)", 
            "separatorLocations": {}, 
            "length": 6, 
            "humanNumber": "4", 
            "position": {
                "y": 0, 
                "x": 8
            }, 
            "solution": "ALIBIS", 
            "id": "4-across"
        }, 
        {
            "direction": "across", 
            "group": [
                "9-across"
            ], 
            "number": 9, 
            "clue": "Wager about a pound (4)", 
            "separatorLocations": {}, 
            "length": 4, 
            "humanNumber": "9", 
            "position": {
                "y": 2, 
                "x": 0
            }, 
            "solution": "BEAT", 
            "id": "9-across"
        }, 
        {
            "direction": "across", 
            "group": [
                "10-across"
            ], 
            "number": 10, 
            "clue": "Fail to honour commitments to one's class? (4,6)", 
            "separatorLocations": {
                ",": [
                    4
                ]
            }, 
            "length": 10, 
            "humanNumber": "10", 
            "position": {
                "y": 2, 
                "x": 5
            }, 
            "solution": "PLAYTRUANT", 
            "id": "10-across"
        }, 
        {
            "direction": "across", 
            "group": [
                "11-across"
            ], 
            "number": 11, 
            "clue": "One must back the law to some degree in Africa (6)", 
            "separatorLocations": {}, 
            "length": 6, 
            "humanNumber": "11", 
            "position": {
                "y": 4, 
                "x": 0
            }, 
            "solution": "MALAWI", 
            "id": "11-across"
        }, 
        {
            "direction": "across", 
            "group": [
                "12-across"
            ], 
            "number": 12, 
            "clue": "Taking someone on of attractive disposition (8)", 
            "separatorLocations": {}, 
            "length": 8, 
            "humanNumber": "12", 
            "position": {
                "y": 4, 
                "x": 7
            }, 
            "solution": "ENGAGING", 
            "id": "12-across"
        }, 
        {
            "direction": "across", 
            "group": [
                "13-across"
            ], 
            "number": 13, 
            "clue": "Gazing about (9)", 
            "separatorLocations": {}, 
            "length": 9, 
            "humanNumber": "13", 
            "position": {
                "y": 6, 
                "x": 0
            }, 
            "solution": "REGARDING", 
            "id": "13-across"
        }, 
        {
            "direction": "across", 
            "group": [
                "15-across"
            ], 
            "number": 15, 
            "clue": "Composed a piece of classical music (4)", 
            "separatorLocations": {}, 
            "length": 4, 
            "humanNumber": "15", 
            "position": {
                "y": 6, 
                "x": 10
            }, 
            "solution": "CALM", 
            "id": "15-across"
        }, 
        {
            "direction": "across", 
            "group": [
                "16-across"
            ], 
            "number": 16, 
            "clue": "Primate embraces son in church (4)", 
            "separatorLocations": {}, 
            "length": 4, 
            "humanNumber": "16", 
            "position": {
                "y": 8, 
                "x": 1
            }, 
            "solution": "APSE", 
            "id": "16-across"
        }, 
        {
            "direction": "across", 
            "group": [
                "17-across"
            ], 
            "number": 17, 
            "clue": "Beneficial, though self-contradictory in parts (9)", 
            "separatorLocations": {}, 
            "length": 9, 
            "humanNumber": "17", 
            "position": {
                "y": 8, 
                "x": 6
            }, 
            "solution": "WHOLESOME", 
            "id": "17-across"
        }, 
        {
            "direction": "across", 
            "group": [
                "21-across"
            ], 
            "number": 21, 
            "clue": "It's a man found shipwrecked on a Pacific island (8)", 
            "separatorLocations": {}, 
            "length": 8, 
            "humanNumber": "21", 
            "position": {
                "y": 10, 
                "x": 0
            }, 
            "solution": "TASMANIA", 
            "id": "21-across"
        }, 
        {
            "direction": "across", 
            "group": [
                "22-across"
            ], 
            "number": 22, 
            "clue": "King for half a year and one short day (6)", 
            "separatorLocations": {}, 
            "length": 6, 
            "humanNumber": "22", 
            "position": {
                "y": 10, 
                "x": 9
            }, 
            "solution": "ARTHUR", 
            "id": "22-across"
        }, 
        {
            "direction": "across", 
            "group": [
                "24-across"
            ], 
            "number": 24, 
            "clue": "General still a duke, even if losing his head (10)", 
            "separatorLocations": {}, 
            "length": 10, 
            "humanNumber": "24", 
            "position": {
                "y": 12, 
                "x": 0
            }, 
            "solution": "WELLINGTON", 
            "id": "24-across"
        }, 
        {
            "direction": "across", 
            "group": [
                "25-across"
            ], 
            "number": 25, 
            "clue": "Tax office (4)", 
            "separatorLocations": {}, 
            "length": 4, 
            "humanNumber": "25", 
            "position": {
                "y": 12, 
                "x": 11
            }, 
            "solution": "DUTY", 
            "id": "25-across"
        }, 
        {
            "direction": "across", 
            "group": [
                "26-across"
            ], 
            "number": 26, 
            "clue": "Is among those left to fight (6)", 
            "separatorLocations": {}, 
            "length": 6, 
            "humanNumber": "26", 
            "position": {
                "y": 14, 
                "x": 1
            }, 
            "solution": "RESIST", 
            "id": "26-across"
        }, 
        {
            "direction": "across", 
            "group": [
                "27-across"
            ], 
            "number": 27, 
            "clue": "Rotten theologian in crooked deal (6)", 
            "separatorLocations": {}, 
            "length": 6, 
            "humanNumber": "27", 
            "position": {
                "y": 14, 
                "x": 8
            }, 
            "solution": "ADDLED", 
            "id": "27-across"
        }, 
        {
            "direction": "down", 
            "group": [
                "1-down"
            ], 
            "number": 1, 
            "clue": "Cheer a team endlessly at entry (7)", 
            "separatorLocations": {}, 
            "length": 7, 
            "humanNumber": "1", 
            "position": {
                "y": 0, 
                "x": 1
            }, 
            "solution": "ELEVATE", 
            "id": "1-down"
        }, 
        {
            "direction": "down", 
            "group": [
                "2-down"
            ], 
            "number": 2, 
            "clue": "He's paid to say nothing (5)", 
            "separatorLocations": {}, 
            "length": 5, 
            "humanNumber": "2", 
            "position": {
                "y": 0, 
                "x": 3
            }, 
            "solution": "EXTRA", 
            "id": "2-down"
        }, 
        {
            "direction": "down", 
            "group": [
                "3-down"
            ], 
            "number": 3, 
            "clue": "Suggested one politician was untruthful (7)", 
            "separatorLocations": {}, 
            "length": 7, 
            "humanNumber": "3", 
            "position": {
                "y": 0, 
                "x": 5
            }, 
            "solution": "IMPLIED", 
            "id": "3-down"
        }, 
        {
            "direction": "down", 
            "group": [
                "5-down"
            ], 
            "number": 5, 
            "clue": "Dismisses a proposal to start moving (4,2)", 
            "separatorLocations": {
                ",": [
                    4
                ]
            }, 
            "length": 6, 
            "humanNumber": "5", 
            "position": {
                "y": 0, 
                "x": 9
            }, 
            "solution": "LETSGO", 
            "id": "5-down"
        }, 
        {
            "direction": "down", 
            "group": [
                "6-down"
            ], 
            "number": 6, 
            "clue": "Unhappy with split in state of Kentucky? (9)", 
            "separatorLocations": {}, 
            "length": 9, 
            "humanNumber": "6", 
            "position": {
                "y": 0, 
                "x": 11
            }, 
            "solution": "BLUEGRASS", 
            "id": "6-down"
        }, 
        {
            "direction": "down", 
            "group": [
                "7-down"
            ], 
            "number": 7, 
            "clue": "Work for Labour, for example (7)", 
            "separatorLocations": {}, 
            "length": 7, 
            "humanNumber": "7", 
            "position": {
                "y": 0, 
                "x": 13
            }, 
            "solution": "SYNONYM", 
            "id": "7-down"
        }, 
        {
            "direction": "down", 
            "group": [
                "8-down"
            ], 
            "number": 8, 
            "clue": "Dare any health resort claim that all its residents are? (4,3,6)", 
            "separatorLocations": {
                ",": [
                    4, 
                    7
                ]
            }, 
            "length": 13, 
            "humanNumber": "8", 
            "position": {
                "y": 1, 
                "x": 7
            }, 
            "solution": "HALEANDHEARTY", 
            "id": "8-down"
        }, 
        {
            "direction": "down", 
            "group": [
                "14-down"
            ], 
            "number": 14, 
            "clue": "See lambs going round in flocks together (9)", 
            "separatorLocations": {}, 
            "length": 9, 
            "humanNumber": "14", 
            "position": {
                "y": 6, 
                "x": 3
            }, 
            "solution": "ASSEMBLES", 
            "id": "14-down"
        }, 
        {
            "direction": "down", 
            "group": [
                "16-down"
            ], 
            "number": 16, 
            "clue": "There's no accounting for his performance (7)", 
            "separatorLocations": {}, 
            "length": 7, 
            "humanNumber": "16", 
            "position": {
                "y": 8, 
                "x": 1
            }, 
            "solution": "AMATEUR", 
            "id": "16-down"
        }, 
        {
            "direction": "down", 
            "group": [
                "18-down"
            ], 
            "number": 18, 
            "clue": "Erudite composer shown the way out (7)", 
            "separatorLocations": {}, 
            "length": 7, 
            "humanNumber": "18", 
            "position": {
                "y": 8, 
                "x": 9
            }, 
            "solution": "LEARNED", 
            "id": "18-down"
        }, 
        {
            "direction": "down", 
            "group": [
                "19-down"
            ], 
            "number": 19, 
            "clue": "Set off on horseback? (7)", 
            "separatorLocations": {}, 
            "length": 7, 
            "humanNumber": "19", 
            "position": {
                "y": 8, 
                "x": 13
            }, 
            "solution": "MOUNTED", 
            "id": "19-down"
        }, 
        {
            "direction": "down", 
            "group": [
                "20-down"
            ], 
            "number": 20, 
            "clue": "Fruit with the top off is still fruit (6)", 
            "separatorLocations": {}, 
            "length": 6, 
            "humanNumber": "20", 
            "position": {
                "y": 9, 
                "x": 5
            }, 
            "solution": "ANANAS", 
            "id": "20-down"
        }, 
        {
            "direction": "down", 
            "group": [
                "23-down"
            ], 
            "number": 23, 
            "clue": "Boy, it rises - and falls! (5)", 
            "separatorLocations": {}, 
            "length": 5, 
            "humanNumber": "23", 
            "position": {
                "y": 10, 
                "x": 11
            }, 
            "solution": "TIDAL", 
            "id": "23-down"
        }
    ], 
    "date": 998870400000, 
    "solutionAvailable": true, 
    "id": "crosswords/cryptic/22298", 
    "dimensions": {
        "rows": 15, 
        "cols": 15
    }
}