{
    "name": "Prize crossword No 22,041", 
    "creator": {
        "webUrl": "https://www.theguardian.com/profile/araucaria", 
        "name": "Araucaria"
    }, 
    "dateSolutionAvailable": 973296000000, 
    "number": 22041, 
    "crosswordType": "prize", 
    "entries": [
        {
            "direction": "across", 
            "group": [
                "7-across"
            ], 
            "number": 7, 
            "clue": "Voices of disapproval about fool getting mackerel (7)", 
            "separatorLocations": {}, 
            "length": 7, 
            "humanNumber": "7", 
            "position": {
                "y": 1, 
                "x": 0
            }, 
            "solution": "BONITOS", 
            "id": "7-across"
        }, 
        {
            "direction": "across", 
            "group": [
                "8-across"
            ], 
            "number": 8, 
            "clue": "Light roll gives spirit to revolutionary (7)", 
            "separatorLocations": {}, 
            "length": 7, 
            "humanNumber": "8", 
            "position": {
                "y": 1, 
                "x": 8
            }, 
            "solution": "BRIOCHE", 
            "id": "8-across"
        }, 
        {
            "direction": "across", 
            "group": [
                "10-across"
            ], 
            "number": 10, 
            "clue": "Liberal revolution gets the spirit (6)", 
            "separatorLocations": {}, 
            "length": 6, 
            "humanNumber": "10", 
            "position": {
                "y": 3, 
                "x": 0
            }, 
            "solution": "BLITHE", 
            "id": "10-across"
        }, 
        {
            "direction": "across", 
            "group": [
                "11-across"
            ], 
            "number": 11, 
            "clue": "In the cinema Mary's choice falls on Harrison (8)", 
            "separatorLocations": {}, 
            "length": 8, 
            "humanNumber": "11", 
            "position": {
                "y": 3, 
                "x": 7
            }, 
            "solution": "PICKFORD", 
            "id": "11-across"
        }, 
        {
            "direction": "across", 
            "group": [
                "12-across", 
                "18-down"
            ], 
            "number": 12, 
            "clue": "With the 6th 2 one is a witch - about right, a feminist! (4-7)", 
            "separatorLocations": {
                "-": [
                    4
                ]
            }, 
            "length": 4, 
            "humanNumber": "12", 
            "position": {
                "y": 5, 
                "x": 0
            }, 
            "solution": "HARD", 
            "id": "12-across"
        }, 
        {
            "direction": "across", 
            "group": [
                "13-across"
            ], 
            "number": 13, 
            "clue": "Tall chap lying down found life real and earnest (10)", 
            "separatorLocations": {}, 
            "length": 10, 
            "humanNumber": "13", 
            "position": {
                "y": 5, 
                "x": 5
            }, 
            "solution": "LONGFELLOW", 
            "id": "13-across"
        }, 
        {
            "direction": "across", 
            "group": [
                "14-across"
            ], 
            "number": 14, 
            "clue": "Plagal mode: get windy after taking syringe: I only hope AA can make it (11)", 
            "separatorLocations": {}, 
            "length": 11, 
            "humanNumber": "14", 
            "position": {
                "y": 7, 
                "x": 2
            }, 
            "solution": "HYPOAEOLIAN", 
            "id": "14-across"
        }, 
        {
            "direction": "across", 
            "group": [
                "19-across"
            ], 
            "number": 19, 
            "clue": "Conductor's role reversing old car (6-4)", 
            "separatorLocations": {
                "-": [
                    6
                ]
            }, 
            "length": 10, 
            "humanNumber": "19", 
            "position": {
                "y": 9, 
                "x": 0
            }, 
            "solution": "RATTLETRAP", 
            "id": "19-across"
        }, 
        {
            "direction": "across", 
            "group": [
                "22-across"
            ], 
            "number": 22, 
            "clue": "With the last 2 one is a piece of, say, 7 and 10, this and 17's outside (4)", 
            "separatorLocations": {}, 
            "length": 4, 
            "humanNumber": "22", 
            "position": {
                "y": 9, 
                "x": 11
            }, 
            "solution": "GOOD", 
            "id": "22-across"
        }, 
        {
            "direction": "across", 
            "group": [
                "23-across"
            ], 
            "number": 23, 
            "clue": "A stroke by the French: provide a detachment (8)", 
            "separatorLocations": {}, 
            "length": 8, 
            "humanNumber": "23", 
            "position": {
                "y": 11, 
                "x": 0
            }, 
            "solution": "UNCOUPLE", 
            "id": "23-across"
        }, 
        {
            "direction": "across", 
            "group": [
                "24-across"
            ], 
            "number": 24, 
            "clue": "\"You stinker!\" cried Archimedes (6)", 
            "separatorLocations": {}, 
            "length": 6, 
            "humanNumber": "24", 
            "position": {
                "y": 11, 
                "x": 9
            }, 
            "solution": "EUREKA", 
            "id": "24-across"
        }, 
        {
            "direction": "across", 
            "group": [
                "25-across"
            ], 
            "number": 25, 
            "clue": "With the 4th 2 one has service backing for African country (3,2,2)", 
            "separatorLocations": {
                ",": [
                    3, 
                    5
                ]
            }, 
            "length": 7, 
            "humanNumber": "25", 
            "position": {
                "y": 13, 
                "x": 0
            }, 
            "solution": "FARTOGO", 
            "id": "25-across"
        }, 
        {
            "direction": "across", 
            "group": [
                "26-across"
            ], 
            "number": 26, 
            "clue": "One who won't drink isn't commonly going to convict (7)", 
            "separatorLocations": {}, 
            "length": 7, 
            "humanNumber": "26", 
            "position": {
                "y": 13, 
                "x": 8
            }, 
            "solution": "ATTAINT", 
            "id": "26-across"
        }, 
        {
            "direction": "down", 
            "group": [
                "1-down"
            ], 
            "number": 1, 
            "clue": "Sophisticated guy - don't give him a hot dog! (4,3)", 
            "separatorLocations": {
                ",": [
                    4
                ]
            }, 
            "length": 7, 
            "humanNumber": "1", 
            "position": {
                "y": 0, 
                "x": 1
            }, 
            "solution": "COOLCAT", 
            "id": "1-down"
        }, 
        {
            "direction": "down", 
            "group": [
                "2-down"
            ], 
            "number": 2, 
            "clue": "Time of arrival sees John hot on Robin (8)", 
            "separatorLocations": {}, 
            "length": 8, 
            "humanNumber": "2", 
            "position": {
                "y": 0, 
                "x": 3
            }, 
            "solution": "BIRTHDAY", 
            "id": "2-down"
        }, 
        {
            "direction": "down", 
            "group": [
                "3-down"
            ], 
            "number": 3, 
            "clue": "Sick? On the contrary: it's somebody's 2 in song (6)", 
            "separatorLocations": {}, 
            "length": 6, 
            "humanNumber": "3", 
            "position": {
                "y": 0, 
                "x": 5
            }, 
            "solution": "NOWELL", 
            "id": "3-down"
        }, 
        {
            "direction": "down", 
            "group": [
                "4-down"
            ], 
            "number": 4, 
            "clue": "With the 2nd 2 one sees people entering another gulf (8)", 
            "separatorLocations": {}, 
            "length": 8, 
            "humanNumber": "4", 
            "position": {
                "y": 0, 
                "x": 9
            }, 
            "solution": "GRACEFUL", 
            "id": "4-down"
        }, 
        {
            "direction": "down", 
            "group": [
                "5-down"
            ], 
            "number": 5, 
            "clue": "With the 3rd 2 one would nearly enter successive notes (6)", 
            "separatorLocations": {}, 
            "length": 6, 
            "humanNumber": "5", 
            "position": {
                "y": 0, 
                "x": 11
            }, 
            "solution": "WOEFUL", 
            "id": "5-down"
        }, 
        {
            "direction": "down", 
            "group": [
                "6-down"
            ], 
            "number": 6, 
            "clue": "Heat preserver from nethermost hell (7)", 
            "separatorLocations": {}, 
            "length": 7, 
            "humanNumber": "6", 
            "position": {
                "y": 0, 
                "x": 13
            }, 
            "solution": "THERMOS", 
            "id": "6-down"
        }, 
        {
            "direction": "down", 
            "group": [
                "9-down"
            ], 
            "number": 9, 
            "clue": "With the 5th 2 one is to attend between Frank and Edward (4-7)", 
            "separatorLocations": {
                "-": [
                    4
                ]
            }, 
            "length": 11, 
            "humanNumber": "9", 
            "position": {
                "y": 2, 
                "x": 7
            }, 
            "solution": "OPENHEARTED", 
            "id": "9-down"
        }, 
        {
            "direction": "down", 
            "group": [
                "15-down"
            ], 
            "number": 15, 
            "clue": "PTO for the complete attendant (8)", 
            "separatorLocations": {}, 
            "length": 8, 
            "humanNumber": "15", 
            "position": {
                "y": 7, 
                "x": 5
            }, 
            "solution": "OVERPAGE", 
            "id": "15-down"
        }, 
        {
            "direction": "down", 
            "group": [
                "16-down"
            ], 
            "number": 16, 
            "clue": "Shearer keeping Halliwell from Constantine, perhaps (8)", 
            "separatorLocations": {}, 
            "length": 8, 
            "humanNumber": "16", 
            "position": {
                "y": 7, 
                "x": 11
            }, 
            "solution": "ALGERIAN", 
            "id": "16-down"
        }, 
        {
            "direction": "down", 
            "group": [
                "17-down"
            ], 
            "number": 17, 
            "clue": "Refuse is always increasing (7)", 
            "separatorLocations": {}, 
            "length": 7, 
            "humanNumber": "17", 
            "position": {
                "y": 8, 
                "x": 1
            }, 
            "solution": "GAINSAY", 
            "id": "17-down"
        }, 
        {
            "direction": "down", 
            "group": [
                "12-across", 
                "18-down"
            ], 
            "number": 18, 
            "clue": "See 12 (7)", 
            "separatorLocations": {
                "-": []
            }, 
            "length": 7, 
            "humanNumber": "18", 
            "position": {
                "y": 8, 
                "x": 13
            }, 
            "solution": "WORKING", 
            "id": "18-down"
        }, 
        {
            "direction": "down", 
            "group": [
                "20-down"
            ], 
            "number": 20, 
            "clue": "Was attracted by authority in its entirety? (4,2)", 
            "separatorLocations": {
                ",": [
                    4
                ]
            }, 
            "length": 6, 
            "humanNumber": "20", 
            "position": {
                "y": 9, 
                "x": 3
            }, 
            "solution": "TOOKTO", 
            "id": "20-down"
        }, 
        {
            "direction": "down", 
            "group": [
                "21-down"
            ], 
            "number": 21, 
            "clue": "With the 1st 2 one is quite often with 22 (6)", 
            "separatorLocations": {}, 
            "length": 6, 
            "humanNumber": "21", 
            "position": {
                "y": 9, 
                "x": 9
            }, 
            "solution": "PRETTY", 
            "id": "21-down"
        }
    ], 
    "date": 972691200000, 
    "solutionAvailable": true, 
    "id": "crosswords/prize/22041", 
    "dimensions": {
        "rows": 15, 
        "cols": 15
    }
}