{
    "id": "crosswords/cryptic/25722",
    "number": 25722,
    "name": "Cryptic crossword No 25,722",
    "creator": {
        "name": "Audreus",
        "webUrl": "https://www.theguardian.com/profile/audreus"
    },
    "date": 1345680000000,
    "webPublicationDate": 1345676400000,
    "entries": [
        {
            "id": "4-across",
            "number": 4,
            "humanNumber": "4",
            "clue": "Besotted with acting, claims a bit of talent (6)",
            "direction": "across",
            "length": 6,
            "group": [
                "4-across"
            ],
            "position": {
                "x": 0,
                "y": 1
            },
            "separatorLocations": {},
            "solution": "DOTING"
        },
        {
            "id": "6-across",
            "number": 6,
            "humanNumber": "6",
            "clue": "Inwardly unfeeling, succumbs to those that won't be moved (8)",
            "direction": "across",
            "length": 8,
            "group": [
                "6-across"
            ],
            "position": {
                "x": 7,
                "y": 1
            },
            "separatorLocations": {},
            "solution": "DIEHARDS"
        },
        {
            "id": "9-across",
            "number": 9,
            "humanNumber": "9",
            "clue": "For such short-sightedness I pay more outrageously \u2014 not again! (6)",
            "direction": "across",
            "length": 6,
            "group": [
                "9-across"
            ],
            "position": {
                "x": 0,
                "y": 3
            },
            "separatorLocations": {},
            "solution": "MYOPIA"
        },
        {
            "id": "10-across",
            "number": 10,
            "humanNumber": "10",
            "clue": "Pretty big: when carrying drug can be taken by force (8)",
            "direction": "across",
            "length": 8,
            "group": [
                "10-across"
            ],
            "position": {
                "x": 7,
                "y": 3
            },
            "separatorLocations": {},
            "solution": "SEIZABLE"
        },
        {
            "id": "11-across",
            "number": 11,
            "humanNumber": "11",
            "clue": "Distinguished detective being sweet (7,4)",
            "direction": "across",
            "length": 11,
            "group": [
                "11-across"
            ],
            "position": {
                "x": 0,
                "y": 5
            },
            "separatorLocations": {
                ",": [
                    7
                ]
            },
            "solution": "SPOTTEDDICK"
        },
        {
            "id": "15-across",
            "number": 15,
            "humanNumber": "15",
            "clue": "Welsh go dancing the cancan? (3-4)",
            "direction": "across",
            "length": 7,
            "group": [
                "15-across"
            ],
            "position": {
                "x": 0,
                "y": 7
            },
            "separatorLocations": {
                "-": [
                    3
                ]
            },
            "solution": "LEGSHOW"
        },
        {
            "id": "17-across",
            "number": 17,
            "humanNumber": "17",
            "clue": "Myself with mate following wordy book concerning loving mother (7)",
            "direction": "across",
            "length": 7,
            "group": [
                "17-across"
            ],
            "position": {
                "x": 8,
                "y": 7
            },
            "separatorLocations": {},
            "solution": "OEDIPAL"
        },
        {
            "id": "18-across",
            "number": 18,
            "humanNumber": "18",
            "clue": "View racket one way in part of northern Europe (11)",
            "direction": "across",
            "length": 11,
            "group": [
                "18-across"
            ],
            "position": {
                "x": 4,
                "y": 9
            },
            "separatorLocations": {},
            "solution": "SCANDINAVIA"
        },
        {
            "id": "22-across",
            "number": 22,
            "humanNumber": "22",
            "clue": "Constable imbibing 21 down: what did you say about being a mixture? (8)",
            "direction": "across",
            "length": 8,
            "group": [
                "22-across"
            ],
            "position": {
                "x": 0,
                "y": 11
            },
            "separatorLocations": {},
            "solution": "PASTICHE"
        },
        {
            "id": "23-across",
            "number": 23,
            "humanNumber": "23",
            "clue": "Some poetry most Anzacs could deliver (6)",
            "direction": "across",
            "length": 6,
            "group": [
                "23-across"
            ],
            "position": {
                "x": 9,
                "y": 11
            },
            "separatorLocations": {},
            "solution": "STANZA"
        },
        {
            "id": "24-across",
            "number": 24,
            "humanNumber": "24",
            "clue": "Complaint of individuals getting out of hospital (8)",
            "direction": "across",
            "length": 8,
            "group": [
                "24-across"
            ],
            "position": {
                "x": 0,
                "y": 13
            },
            "separatorLocations": {},
            "solution": "SHINGLES"
        },
        {
            "id": "25-across",
            "number": 25,
            "humanNumber": "25",
            "clue": "Believe in tick? (6)",
            "direction": "across",
            "length": 6,
            "group": [
                "25-across"
            ],
            "position": {
                "x": 9,
                "y": 13
            },
            "separatorLocations": {},
            "solution": "CREDIT"
        },
        {
            "id": "1-down",
            "number": 1,
            "humanNumber": "1",
            "clue": "Oil-producing nation (6)",
            "direction": "down",
            "length": 6,
            "group": [
                "1-down"
            ],
            "position": {
                "x": 4,
                "y": 0
            },
            "separatorLocations": {},
            "solution": "ANOINT"
        },
        {
            "id": "2-down",
            "number": 2,
            "humanNumber": "2",
            "clue": "Safe bet, said plausible gangster (10)",
            "direction": "down",
            "length": 10,
            "group": [
                "2-down"
            ],
            "position": {
                "x": 8,
                "y": 0
            },
            "separatorLocations": {},
            "solution": "LIKELIHOOD"
        },
        {
            "id": "3-down",
            "number": 3,
            "humanNumber": "3",
            "clue": "Wife greeting snoring youngster, a remarkable person (5-3)",
            "direction": "down",
            "length": 8,
            "group": [
                "3-down"
            ],
            "position": {
                "x": 10,
                "y": 0
            },
            "separatorLocations": {
                "-": [
                    5
                ]
            },
            "solution": "WHIZZKID"
        },
        {
            "id": "4-down",
            "number": 4,
            "humanNumber": "4",
            "clue": "Maybe some lads like old-fashioned girls (8)",
            "direction": "down",
            "length": 8,
            "group": [
                "4-down"
            ],
            "position": {
                "x": 0,
                "y": 1
            },
            "separatorLocations": {},
            "solution": "DAMOSELS"
        },
        {
            "id": "5-down",
            "number": 5,
            "humanNumber": "5",
            "clue": "Taking pains done with circulating job centre (8)",
            "direction": "down",
            "length": 8,
            "group": [
                "5-down"
            ],
            "position": {
                "x": 2,
                "y": 1
            },
            "separatorLocations": {},
            "solution": "THOROUGH"
        },
        {
            "id": "7-down",
            "number": 7,
            "humanNumber": "7",
            "clue": "First boys to enter when teacher's around could be spare (4)",
            "direction": "down",
            "length": 4,
            "group": [
                "7-down"
            ],
            "position": {
                "x": 12,
                "y": 1
            },
            "separatorLocations": {},
            "solution": "RIBS"
        },
        {
            "id": "8-down",
            "number": 8,
            "humanNumber": "8",
            "clue": "Cast of beginners to study hard, exercising daily (4)",
            "direction": "down",
            "length": 4,
            "group": [
                "8-down"
            ],
            "position": {
                "x": 14,
                "y": 1
            },
            "separatorLocations": {},
            "solution": "SHED"
        },
        {
            "id": "12-down",
            "number": 12,
            "humanNumber": "12",
            "clue": "Shabby dog's two orders? (4,2,4)",
            "direction": "down",
            "length": 10,
            "group": [
                "12-down"
            ],
            "position": {
                "x": 6,
                "y": 5
            },
            "separatorLocations": {
                ",": [
                    4,
                    6
                ]
            },
            "solution": "DOWNATHEEL"
        },
        {
            "id": "13-down",
            "number": 13,
            "humanNumber": "13",
            "clue": "PS And I've managed to be afflicted with a swelling in a leg joint (8)",
            "direction": "down",
            "length": 8,
            "group": [
                "13-down"
            ],
            "position": {
                "x": 12,
                "y": 6
            },
            "separatorLocations": {},
            "solution": "SPAVINED"
        },
        {
            "id": "14-down",
            "number": 14,
            "humanNumber": "14",
            "clue": "Poor man admits late starter's affable (8)",
            "direction": "down",
            "length": 8,
            "group": [
                "14-down"
            ],
            "position": {
                "x": 14,
                "y": 6
            },
            "separatorLocations": {},
            "solution": "PLEASANT"
        },
        {
            "id": "16-down",
            "number": 16,
            "humanNumber": "16",
            "clue": "Historic town, lice infection over, guarded by witches (8)",
            "direction": "down",
            "length": 8,
            "group": [
                "16-down"
            ],
            "position": {
                "x": 4,
                "y": 7
            },
            "separatorLocations": {},
            "solution": "HASTINGS"
        },
        {
            "id": "19-down",
            "number": 19,
            "humanNumber": "19",
            "clue": "Quality of a busy tea urn (6)",
            "direction": "down",
            "length": 6,
            "group": [
                "19-down"
            ],
            "position": {
                "x": 10,
                "y": 9
            },
            "separatorLocations": {},
            "solution": "NATURE"
        },
        {
            "id": "20-down",
            "number": 20,
            "humanNumber": "20",
            "clue": "You get ninny turning up with tree from Java (4)",
            "direction": "down",
            "length": 4,
            "group": [
                "20-down"
            ],
            "position": {
                "x": 0,
                "y": 10
            },
            "separatorLocations": {},
            "solution": "UPAS"
        },
        {
            "id": "21-down",
            "number": 21,
            "humanNumber": "21",
            "clue": "Good man's into first-class wine (4)",
            "direction": "down",
            "length": 4,
            "group": [
                "21-down"
            ],
            "position": {
                "x": 2,
                "y": 10
            },
            "separatorLocations": {},
            "solution": "ASTI"
        }
    ],
    "solutionAvailable": true,
    "dateSolutionAvailable": 1345676400000,
    "dimensions": {
        "cols": 15,
        "rows": 15
    },
    "crosswordType": "cryptic",
    "pdf": "http://static.guim.co.uk/crosswords/pdfs/gdn.cryptic.20120823.pdf",
    "_gridType": "M33"
}