{
    "name": "Cryptic crossword No 26,583", 
    "creator": {
        "webUrl": "http://www.theguardian.com/profile/brummie", 
        "name": "Brummie"
    }, 
    "dateSolutionAvailable": 1432767600000, 
    "number": 26583, 
    "crosswordType": "cryptic", 
    "entries": [
        {
            "direction": "across", 
            "group": [
                "9-across"
            ], 
            "number": 9, 
            "clue": "Solvers no good as babies? (5)", 
            "separatorLocations": {}, 
            "length": 5, 
            "humanNumber": "9", 
            "position": {
                "y": 1, 
                "x": 0
            }, 
            "solution": "YOUNG", 
            "id": "9-across"
        }, 
        {
            "direction": "across", 
            "group": [
                "10-across"
            ], 
            "number": 10, 
            "clue": "Mole, a musician getting ready to enthral a king's mistress? (9)", 
            "separatorLocations": {}, 
            "length": 9, 
            "humanNumber": "10", 
            "position": {
                "y": 1, 
                "x": 6
            }, 
            "solution": "TUNNELLER", 
            "id": "10-across"
        }, 
        {
            "direction": "across", 
            "group": [
                "11-across"
            ], 
            "number": 11, 
            "clue": "Pit workers possibly round river front \u2014 god! (9)", 
            "separatorLocations": {}, 
            "length": 9, 
            "humanNumber": "11", 
            "position": {
                "y": 3, 
                "x": 0
            }, 
            "solution": "ORCHESTRA", 
            "id": "11-across"
        }, 
        {
            "direction": "across", 
            "group": [
                "12-across", 
                "14-down"
            ], 
            "number": 12, 
            "clue": " Virginia's classic direction of keeper going to work? (2,3,10)", 
            "separatorLocations": {
                ",": [
                    2, 
                    5
                ]
            }, 
            "length": 5, 
            "humanNumber": "12, 14", 
            "position": {
                "y": 3, 
                "x": 10
            }, 
            "solution": "TOTHE", 
            "id": "12-across"
        }, 
        {
            "direction": "across", 
            "group": [
                "13-across"
            ], 
            "number": 13, 
            "clue": "State's contribution to ransom, a liability (7)", 
            "separatorLocations": {}, 
            "length": 7, 
            "humanNumber": "13", 
            "position": {
                "y": 5, 
                "x": 0
            }, 
            "solution": "SOMALIA", 
            "id": "13-across"
        }, 
        {
            "direction": "across", 
            "group": [
                "15-across"
            ], 
            "number": 15, 
            "clue": "Former president's protective of society people (7)", 
            "separatorLocations": {}, 
            "length": 7, 
            "humanNumber": "15", 
            "position": {
                "y": 5, 
                "x": 8
            }, 
            "solution": "PERSONS", 
            "id": "15-across"
        }, 
        {
            "direction": "across", 
            "group": [
                "17-across"
            ], 
            "number": 17, 
            "clue": "Reverse the setting up of one vulgar doctor (5)", 
            "separatorLocations": {}, 
            "length": 5, 
            "humanNumber": "17", 
            "position": {
                "y": 7, 
                "x": 0
            }, 
            "solution": "UNRIG", 
            "id": "17-across"
        }, 
        {
            "direction": "across", 
            "group": [
                "18-across"
            ], 
            "number": 18, 
            "clue": "Lad, the almost disappearing one (3)", 
            "separatorLocations": {}, 
            "length": 3, 
            "humanNumber": "18", 
            "position": {
                "y": 7, 
                "x": 6
            }, 
            "solution": "YOU", 
            "id": "18-across"
        }, 
        {
            "direction": "across", 
            "group": [
                "20-across"
            ], 
            "number": 20, 
            "clue": "Who's part of the movie host's run? (5)", 
            "separatorLocations": {}, 
            "length": 5, 
            "humanNumber": "20", 
            "position": {
                "y": 7, 
                "x": 10
            }, 
            "solution": "EXTRA", 
            "id": "20-across"
        }, 
        {
            "direction": "across", 
            "group": [
                "22-across"
            ], 
            "number": 22, 
            "clue": "Benjamin, a familiar national figure? (7)", 
            "separatorLocations": {}, 
            "length": 7, 
            "humanNumber": "22", 
            "position": {
                "y": 9, 
                "x": 0
            }, 
            "solution": "BRITTEN", 
            "id": "22-across"
        }, 
        {
            "direction": "across", 
            "group": [
                "25-across"
            ], 
            "number": 25, 
            "clue": "Almost express contentment with chamber music man (7)", 
            "separatorLocations": {}, 
            "length": 7, 
            "humanNumber": "25", 
            "position": {
                "y": 9, 
                "x": 8
            }, 
            "solution": "PURCELL", 
            "id": "25-across"
        }, 
        {
            "direction": "across", 
            "group": [
                "26-across"
            ], 
            "number": 26, 
            "clue": "Not much of a role for top actor of advanced circle (5)", 
            "separatorLocations": {}, 
            "length": 5, 
            "humanNumber": "26", 
            "position": {
                "y": 11, 
                "x": 0
            }, 
            "solution": "CAMEO", 
            "id": "26-across"
        }, 
        {
            "direction": "across", 
            "group": [
                "27-across"
            ], 
            "number": 27, 
            "clue": "Low density rock, possibly providing a background for hotel lobbies? (4,5)", 
            "separatorLocations": {
                ",": [
                    4
                ]
            }, 
            "length": 9, 
            "humanNumber": "27", 
            "position": {
                "y": 11, 
                "x": 6
            }, 
            "solution": "MOODMUSIC", 
            "id": "27-across"
        }, 
        {
            "direction": "across", 
            "group": [
                "30-across"
            ], 
            "number": 30, 
            "clue": "Less complicated clue in lower case (9)", 
            "separatorLocations": {}, 
            "length": 9, 
            "humanNumber": "30", 
            "position": {
                "y": 13, 
                "x": 0
            }, 
            "solution": "MINUSCULE", 
            "id": "30-across"
        }, 
        {
            "direction": "across", 
            "group": [
                "31-across"
            ], 
            "number": 31, 
            "clue": "Fine for Scots to have English escort (5)", 
            "separatorLocations": {}, 
            "length": 5, 
            "humanNumber": "31", 
            "position": {
                "y": 13, 
                "x": 10
            }, 
            "solution": "GUIDE", 
            "id": "31-across"
        }, 
        {
            "direction": "down", 
            "group": [
                "1-down"
            ], 
            "number": 1, 
            "clue": "Party politics covers up blunder (4)", 
            "separatorLocations": {}, 
            "length": 4, 
            "humanNumber": "1", 
            "position": {
                "y": 0, 
                "x": 0
            }, 
            "solution": "TYPO", 
            "id": "1-down"
        }, 
        {
            "direction": "down", 
            "group": [
                "2-down"
            ], 
            "number": 2, 
            "clue": "Beaten mid-clue by setter's ultimate instrument (8)", 
            "separatorLocations": {}, 
            "length": 8, 
            "humanNumber": "2", 
            "position": {
                "y": 0, 
                "x": 2
            }, 
            "solution": "DULCIMER", 
            "id": "2-down"
        }, 
        {
            "direction": "down", 
            "group": [
                "3-down"
            ], 
            "number": 3, 
            "clue": "Losing against obscure illness (4)", 
            "separatorLocations": {}, 
            "length": 4, 
            "humanNumber": "3", 
            "position": {
                "y": 0, 
                "x": 4
            }, 
            "solution": "AGUE", 
            "id": "3-down"
        }, 
        {
            "direction": "down", 
            "group": [
                "4-down"
            ], 
            "number": 4, 
            "clue": "Stuart A. played with Yes, the rock group? (8)", 
            "separatorLocations": {}, 
            "length": 8, 
            "humanNumber": "4", 
            "position": {
                "y": 0, 
                "x": 6
            }, 
            "solution": "STATUARY", 
            "id": "4-down"
        }, 
        {
            "direction": "down", 
            "group": [
                "5-down"
            ], 
            "number": 5, 
            "clue": "Make a pitch: \"Hull's location is on the up, rather flamboyant\" (6)", 
            "separatorLocations": {}, 
            "length": 6, 
            "humanNumber": "5", 
            "position": {
                "y": 0, 
                "x": 8
            }, 
            "solution": "ENCAMP", 
            "id": "5-down"
        }, 
        {
            "direction": "down", 
            "group": [
                "6-down"
            ], 
            "number": 6, 
            "clue": "I agree, Terry's worried about Nuneaton centre's past (10)", 
            "separatorLocations": {}, 
            "length": 10, 
            "humanNumber": "6", 
            "position": {
                "y": 0, 
                "x": 10
            }, 
            "solution": "YESTERYEAR", 
            "id": "6-down"
        }, 
        {
            "direction": "down", 
            "group": [
                "7-down"
            ], 
            "number": 7, 
            "clue": "Fate is cold and reluctant before love (6)", 
            "separatorLocations": {}, 
            "length": 6, 
            "humanNumber": "7", 
            "position": {
                "y": 0, 
                "x": 12
            }, 
            "solution": "CLOTHO", 
            "id": "7-down"
        }, 
        {
            "direction": "down", 
            "group": [
                "26-down", 
                "8-down"
            ], 
            "number": 8, 
            "clue": "See 26", 
            "separatorLocations": {
                ",": []
            }, 
            "length": 4, 
            "humanNumber": "8", 
            "position": {
                "y": 0, 
                "x": 14
            }, 
            "solution": "TRUE", 
            "id": "8-down"
        }, 
        {
            "direction": "down", 
            "group": [
                "13-down"
            ], 
            "number": 13, 
            "clue": "Small weak person liable to get lit up (5)", 
            "separatorLocations": {}, 
            "length": 5, 
            "humanNumber": "13", 
            "position": {
                "y": 5, 
                "x": 0
            }, 
            "solution": "SQUIB", 
            "id": "13-down"
        }, 
        {
            "direction": "down", 
            "group": [
                "12-across", 
                "14-down"
            ], 
            "number": 14, 
            "clue": "See 12", 
            "separatorLocations": {
                ",": []
            }, 
            "length": 10, 
            "humanNumber": "14", 
            "position": {
                "y": 5, 
                "x": 4
            }, 
            "solution": "LIGHTHOUSE", 
            "id": "14-down"
        }, 
        {
            "direction": "down", 
            "group": [
                "16-down"
            ], 
            "number": 16, 
            "clue": "One could be wrapped up in this Walsh novel (5)", 
            "separatorLocations": {}, 
            "length": 5, 
            "humanNumber": "16", 
            "position": {
                "y": 5, 
                "x": 14
            }, 
            "solution": "SHAWL", 
            "id": "16-down"
        }, 
        {
            "direction": "down", 
            "group": [
                "19-down"
            ], 
            "number": 19, 
            "clue": "Parking in sporting run range not established (8)", 
            "separatorLocations": {}, 
            "length": 8, 
            "humanNumber": "19", 
            "position": {
                "y": 7, 
                "x": 8
            }, 
            "solution": "UNPROVEN", 
            "id": "19-down"
        }, 
        {
            "direction": "down", 
            "group": [
                "21-down"
            ], 
            "number": 21, 
            "clue": "Believing it's involved with ethics (8)", 
            "separatorLocations": {}, 
            "length": 8, 
            "humanNumber": "21", 
            "position": {
                "y": 7, 
                "x": 12
            }, 
            "solution": "THEISTIC", 
            "id": "21-down"
        }, 
        {
            "direction": "down", 
            "group": [
                "23-down"
            ], 
            "number": 23, 
            "clue": "Setter's married a foreign female \u2014 so complaint impossible? (6)", 
            "separatorLocations": {}, 
            "length": 6, 
            "humanNumber": "23", 
            "position": {
                "y": 9, 
                "x": 2
            }, 
            "solution": "IMMUNE", 
            "id": "23-down"
        }, 
        {
            "direction": "down", 
            "group": [
                "24-down"
            ], 
            "number": 24, 
            "clue": "Lower than the lowest turned up as rain producer (6)", 
            "separatorLocations": {}, 
            "length": 6, 
            "humanNumber": "24", 
            "position": {
                "y": 9, 
                "x": 6
            }, 
            "solution": "NIMBUS", 
            "id": "24-down"
        }, 
        {
            "direction": "down", 
            "group": [
                "26-down", 
                "8-down"
            ], 
            "number": 26, 
            "clue": " Meteor and small copper rocks occur as predicted (4,4)", 
            "separatorLocations": {
                ",": [
                    4
                ]
            }, 
            "length": 4, 
            "humanNumber": "26, 8", 
            "position": {
                "y": 11, 
                "x": 0
            }, 
            "solution": "COME", 
            "id": "26-down"
        }, 
        {
            "direction": "down", 
            "group": [
                "28-down"
            ], 
            "number": 28, 
            "clue": "Star-struck followers of old lady with judo outfit (4)", 
            "separatorLocations": {}, 
            "length": 4, 
            "humanNumber": "28", 
            "position": {
                "y": 11, 
                "x": 10
            }, 
            "solution": "MAGI", 
            "id": "28-down"
        }, 
        {
            "direction": "down", 
            "group": [
                "29-down"
            ], 
            "number": 29, 
            "clue": "The gang gloated (4)", 
            "separatorLocations": {}, 
            "length": 4, 
            "humanNumber": "29", 
            "position": {
                "y": 11, 
                "x": 14
            }, 
            "solution": "CREW", 
            "id": "29-down"
        }
    ], 
    "date": 1432771200000, 
    "pdf": "http://static.guim.co.uk/crosswords/pdfs/gdn.cryptic.20150528.pdf", 
    "solutionAvailable": true, 
    "id": "crosswords/cryptic/26583", 
    "dimensions": {
        "rows": 15, 
        "cols": 15
    }
}